openfabric_pysdk/__init__.py
openfabric_pysdk/api/__init__.py
openfabric_pysdk/app/__init__.py
openfabric_pysdk/app/app.py
openfabric_pysdk/app/comm.py
openfabric_pysdk/app/worker.py
openfabric_pysdk/benchmark/__init__.py
openfabric_pysdk/benchmark/time_benchmark.py
openfabric_pysdk/context/__init__.py
openfabric_pysdk/context/bar.py
openfabric_pysdk/context/bar_schema.py
openfabric_pysdk/context/message.py
openfabric_pysdk/context/message_schema.py
openfabric_pysdk/context/ray.py
openfabric_pysdk/context/ray_schema.py
openfabric_pysdk/context/state.py
openfabric_pysdk/context/state_schema.py
openfabric_pysdk/engine/__init__.py
openfabric_pysdk/engine/engine.py
openfabric_pysdk/execution/__init__.py
openfabric_pysdk/execution/container.py
openfabric_pysdk/execution/profile.py
openfabric_pysdk/fields/__init__.py
openfabric_pysdk/flask/__init__.py
openfabric_pysdk/flask/core/__init__.py
openfabric_pysdk/flask/rest/__init__.py
openfabric_pysdk/flask/socket/__init__.py
openfabric_pysdk/flask/socket/socketio_client.py
openfabric_pysdk/flask/socket/socketio_server.py
openfabric_pysdk/helper/__init__.py
openfabric_pysdk/helper/proxy.py
openfabric_pysdk/loader/__init__.py
openfabric_pysdk/loader/config.py
openfabric_pysdk/service/__init__.py
openfabric_pysdk/service/config_service.py
openfabric_pysdk/service/remote_service.py
openfabric_pysdk/service/rest_service.py
openfabric_pysdk/service/socket_service.py
openfabric_pysdk/service/swagger_service.py
openfabric_pysdk/starter.py
openfabric_pysdk/store/__init__.py
openfabric_pysdk/store/kvdb.py
openfabric_pysdk/store/lru.py
openfabric_pysdk/store/store.py
openfabric_pysdk/task.py
openfabric_pysdk/transport/__init__.py
openfabric_pysdk/transport/resource_descriptor.py
openfabric_pysdk/transport/rest/__init__.py
openfabric_pysdk/transport/rest/local/__init__.py
openfabric_pysdk/transport/rest/local/benchmark_api.py
openfabric_pysdk/transport/rest/local/config_api.py
openfabric_pysdk/transport/rest/local/execution_api.py
openfabric_pysdk-0.2.8.dist-info/METADATA
openfabric_pysdk-0.2.8.dist-info/WHEEL
openfabric_pysdk-0.2.8.dist-info/RECORD
