Metadata-Version: 2.1
Name: openfabric-pysdk
Version: 0.2.8
Summary: Openfabric Python SDK
Home-page: https://openfabric.ai
Keywords: openfabric,SDK,IoAI
Author: Andrei Tara
Author-email: andrei@openfabric.ai
Requires-Python: >=3.8,<4.0
Classifier: Environment :: Console
Classifier: Operating System :: OS Independent
Classifier: Programming Language :: Python :: 3
Classifier: Programming Language :: Python :: 3.8
Classifier: Programming Language :: Python :: 3.9
Classifier: Programming Language :: Python :: 3.10
Classifier: Programming Language :: Python :: 3.11
Classifier: Topic :: Software Development :: Libraries :: Python Modules
Requires-Dist: Flask (>=2.0.1,<3.0.0)
Requires-Dist: Flask-Cors (>=3.0.10,<4.0.0)
Requires-Dist: Flask-RESTful (>=0.3.9,<0.4.0)
Requires-Dist: Flask-SocketIO (>=5.3.6,<6.0.0)
Requires-Dist: Werkzeug (>=2.0.3)
Requires-Dist: flask-apispec (>=0.11.0,<0.12.0)
Requires-Dist: gevent (>=22.10.2,<23.0.0)
Requires-Dist: gevent-websocket (>=0.10.1,<0.11.0)
Requires-Dist: marshmallow-enum (>=1.5.1,<2.0.0)
Requires-Dist: pickleDB (>=0.9.2,<0.10.0)
Requires-Dist: pyzmq (>=25.1.1,<26.0.0)
Requires-Dist: runstats (>=2.0.0,<3.0.0)
Requires-Dist: socketio-client (>=0.7.2,<0.8.0)
Requires-Dist: tqdm (>=4.62.3,<5.0.0)
Project-URL: Repository, https://github.com/Openfabric/openfabic-pysdk
